langevals_presidio/pii_detection.py
langevals_presidio-0.1.7.dist-info/METADATA
langevals_presidio-0.1.7.dist-info/WHEEL
langevals_presidio-0.1.7.dist-info/RECORD
