Metadata-Version: 2.4
Name: langevals-presidio
Version: 0.1.7
Summary: LangEvals integration for Presidio
License: MIT
Author: Rogerio Chaves
Author-email: rogerio@langwatch.ai
Requires-Python: >=3.11,<4.0
Classifier: License :: OSI Approved :: MIT License
Classifier: Programming Language :: Python :: 3
Classifier: Programming Language :: Python :: 3.11
Classifier: Programming Language :: Python :: 3.12
Classifier: Programming Language :: Python :: 3.13
Classifier: Programming Language :: Python :: 3.14
Requires-Dist: langevals-core (>=0.1.18,<0.2.0)
Requires-Dist: presidio-analyzer (>=2.2.355,<3.0.0)
Requires-Dist: presidio-anonymizer (>=2.2.355,<3.0.0)
Requires-Dist: spacy (==3.7.5)
